{"issue":{"title":"[CF 182] Meta ICON have error ","body":" <p>all fixed in r55,thanks for hard work<sup><br>\r\nR54 fixed the conditions<br>\r\n<del><strong>1.Meta Icon's conditions not working.it's always shown out combat or don't have target</strong></del><br>\r\n<del><strong>2.Cooldown and Cooldown text<br>\r\n<img src=\"http://static.curseforge.net/content/attachments/15/503/meta.PNG\" alt=\"http://static.curseforge.net/content/attachments/15/503/meta.PNG\"><br>\r\nI have 2 target to attack,at first i cast Sunder Armor on A,and cast Colossus Smash ,i switch target to B,when I switch back target A,<br>\r\nMeta Icon only show Colossus Smash's icon ,don't have cooldown and cooldown text.</strong></del></sup></p>\r\n<div><div><div>\n\n```\n{\r\n[\"Type\"] = \"meta\",\r\n[\"Conditions\"] = {\r\n\t{\r\n\t\t[\"Type\"] = \"EXISTS\",\r\n\t\t[\"Unit\"] = \"target\",\r\n\t}, -- [1]\r\n\t{\r\n\t\t[\"Type\"] = \"ALIVE\",\r\n\t\t[\"Unit\"] = \"target\",\r\n\t}, -- [2]\r\n\t{\r\n\t\t[\"Type\"] = \"COMBAT\",\r\n\t}, -- [3]\r\n\t{\r\n\t\t[\"Type\"] = \"REACT\",\r\n\t\t[\"Level\"] = 1,\r\n\t\t[\"Unit\"] = \"target\",\r\n\t}, -- [4]\r\n},\r\n[\"Enabled\"] = true,\r\n[\"Icons\"] = {\r\n\t\"TellMeWhen_Group6_Icon8\", -- [1]\r\n\t\"TellMeWhen_Group5_Icon3\", -- [2]\r\n},\r\n},\r\n\n```\n</div></div>\r\n</div><p>Group5_Icon3<br></p>\r\n<div><div><div>\n\n```\n{\r\n\t[\"ManaCheck\"] = true,\r\n\t[\"ShowTimer\"] = true,\r\n\t[\"Type\"] = \"cooldown\",\r\n\t[\"CooldownShowWhen\"] = \"always\",\r\n\t[\"CooldownCheck\"] = true,\r\n\t[\"RangeCheck\"] = true,\r\n\t[\"Enabled\"] = true,\r\n\t[\"Name\"] = \"Colossus Smash\",\r\n\t[\"UseActvtnOverlay\"] = true,\r\n}, -- [3]\r\n\n```\n</div></div>\r\n</div><p>Group6_Icon8<br>\r\n</p><div><div><div>\n\n```\n{\r\n\t[\"ShowTimer\"] = true,\r\n\t[\"BuffOrDebuff\"] = \"HARMFUL\",\r\n\t[\"Unit\"] = \"target\",\r\n\t[\"Type\"] = \"buff\",\r\n\t[\"FakeHidden\"] = true,\r\n\t[\"Enabled\"] = true,\r\n\t[\"Name\"] = \"Sunder Armor\",\r\n\t[\"BuffShowWhen\"] = \"absent\",\r\n}, -- [8]\r\n\n```\n</div></div>\r\n</div><p><br>\r\nTMW version is R53<br>\r\nthanks all your hard work.<br>\r\nsorry for my bad english.</p> \n<br>\n\n> Posted by CurseForge user <a href=\"https://wow.curseforge.com/members/lsjyzjl\">lsjyzjl</a> | Imported from CurseForge issue <a href=\"https://wow.curseforge.com/projects/tellmewhen/issues/182\">#182</a> | <a href=\"https://github.com/tmw-issue-import/dump/blob/master/html/182.html\">Raw</a>","closed":true,"closed_at":"2011-04-27T05:08:14Z","created_at":"2011-04-26T10:36:42Z","updated_at":"2011-04-27T05:08:14Z","labels":["defect","resolved"]},"comments":[{"body":"<strong>Attachment Added:</strong><a href=\"https://media.forgecdn.net/attachments/76/50/meta.PNG\" target=\"_blank\"> meta.PNG</a><br> <a class=\"e-avatar128 lightbox\" href=\"https://media.forgecdn.net/attachments/76/50/meta.PNG\" title=\"meta.PNG\"> <img src=\"https://media.forgecdn.net/attachments/thumbnails/76/50/126/126/meta.PNG\"> </a> <div class=\"attachment-desc\"> <h4 class=\"attachment-title\">meta.PNG</h4> <p>&lt;p&gt;meta icon&lt;/p&gt;</p> </div> \n<br>\n\n> Posted by CurseForge user <a href=\"https://wow.curseforge.com/members/lsjyzjl\">lsjyzjl</a>","created_at":"2011-04-26T10:36:42Z"}]}