{"issue":{"title":"[CF 316] Rune of Zeth Trink ","body":" <h4>Submitted Via</h4>\r\n<p>Curse Client 4.0.1.112, Microsoft Windows NT 6.0.6002 Service Pack 2</p>\r\n<h4>Installed Version</h4>\r\n<p>4.6.3</p>\r\n<h4>Description</h4>\r\n<p>It cannot track the FL Rune of Zeth trinket. It can track the buff; however, it cannot track the CD. I tried to type the name, shift click, and drag the icon from my spell bar into the grid. Nothing gets it to recognize the trink.</p>\r\n<h4>Installed Addons</h4>\r\n<p>AuctionLite - v1.8.2\r\nCalculator - Calculator 1.6\r\nGatherMate2 - 1.15.2\r\nGatherMate2_Data - v6.8\r\nHealBot Continued - 4.2.2.2\r\nMoveAnything - 12.2.0\r\nOmniCC - 4.2.3\r\nPostal - v3.4.10\r\nQuartz - 3.0.7\r\nRecount - v4.2.0f release\r\nRoutes - v1.4.1\r\nTellMeWhen - 4.6.3</p> \n<br>\n\n> Posted by CurseForge user <a href=\"https://wow.curseforge.com/members/PurpleMurp\">PurpleMurp</a> | Imported from CurseForge issue <a href=\"https://wow.curseforge.com/projects/tellmewhen/issues/316\">#316</a> | <a href=\"https://github.com/tmw-issue-import/dump/blob/master/html/316.html\">Raw</a>","closed":true,"closed_at":"2011-10-27T03:50:17Z","created_at":"2011-10-27T03:43:03Z","updated_at":"2011-10-27T03:50:17Z","labels":["enhancement"]},"comments":[{"body":" <p>Please don't submit tickets through the curse client. Submit them through <a href=\"http://wow.curseforge.com/addons/tellmewhen/tickets\" rel=\"nofollow\">http://wow.curseforge.com/addons/tellmewhen/tickets</a> instead. There is a template that is used for tickets submitted there that contains instructions that you need to follow for me to be able to diagnose the issue you are having.</p> <div class=\"project-issue-comment-body-modified\"> </div> \n<br>\n\n> Posted by CurseForge user <a href=\"https://wow.curseforge.com/members/Cybeloras\">Cybeloras</a>","created_at":"2011-10-27T03:50:17Z"}]}