{"issue":{"title":"[CF 364] Let meta icons check an entire group ","body":" <p>Let users choose a group as an option for a meta icon, and then just scan through the group and grab every icon that is valid and throw them into the meta pool at that position.</p> \n<br>\n\n> Posted by CurseForge user <a href=\"https://wow.curseforge.com/members/Cybeloras\">Cybeloras</a> | Imported from CurseForge issue <a href=\"https://wow.curseforge.com/projects/tellmewhen/issues/364\">#364</a> | <a href=\"https://github.com/tmw-issue-import/dump/blob/master/html/364.html\">Raw</a>","closed":true,"closed_at":"2011-12-04T00:16:37Z","created_at":"2011-12-01T23:32:08Z","updated_at":"2011-12-04T00:16:37Z","labels":["enhancement","resolved"]},"comments":[]}